{
  "hash": "665cc8f3",
  "configHash": "0a64cac8",
  "lockfileHash": "08e33768",
  "browserHash": "f52ef167",
  "optimized": {
    "react/jsx-dev-runtime": {
      "src": "../../node_modules/react/jsx-dev-runtime.js",
      "file": "react_jsx-dev-runtime.js",
      "fileHash": "e53064b0",
      "needsInterop": true
    },
    "react": {
      "src": "../../node_modules/react/index.js",
      "file": "react.js",
      "fileHash": "6f6fcceb",
      "needsInterop": true
    },
    "react-dom/client": {
      "src": "../../node_modules/react-dom/client.js",
      "file": "react-dom_client.js",
      "fileHash": "bf6ccf4a",
      "needsInterop": true
    },
    "@clerk/clerk-react": {
      "src": "../../node_modules/@clerk/clerk-react/dist/index.mjs",
      "file": "@clerk_clerk-react.js",
      "fileHash": "a5b86c73",
      "needsInterop": false
    },
    "react-icons/fa": {
      "src": "../../node_modules/react-icons/fa/index.mjs",
      "file": "react-icons_fa.js",
      "fileHash": "411d5208",
      "needsInterop": false
    },
    "lucide-react": {
      "src": "../../node_modules/lucide-react/dist/esm/lucide-react.js",
      "file": "lucide-react.js",
      "fileHash": "988b0a38",
      "needsInterop": false
    }
  },
  "chunks": {
    "chunk-JJSCUBFW": {
      "file": "chunk-JJSCUBFW.js"
    },
    "chunk-H3AANLML": {
      "file": "chunk-H3AANLML.js"
    }
  }
}